{
  "indexes": {
    "S&P 500": {
      "symbol": "^GSPC",
      "price": 7386.63,
      "change": -16.47,
      "pct_change": -0.22
    },
    "Dow": {
      "symbol": "^DJI",
      "price": 49604.57,
      "change": -83.0,
      "pct_change": -0.17
    },
    "Nasdaq": {
      "symbol": "^IXIC",
      "price": 25991.88,
      "change": -98.86,
      "pct_change": -0.38
    }
  },
  "gainers": [
    {
      "symbol": "LLY",
      "price": 1014.66,
      "change": 24.76,
      "pct_change": 2.5
    },
    {
      "symbol": "MRK",
      "price": 114.64,
      "change": 2.31,
      "pct_change": 2.06
    },
    {
      "symbol": "XOM",
      "price": 162.42,
      "change": 1.93,
      "pct_change": 1.2
    }
  ],
  "losers": [
    {
      "symbol": "AMZN",
      "price": 259.19,
      "change": -5.71,
      "pct_change": -2.16
    },
    {
      "symbol": "GOOGL",
      "price": 390.34,
      "change": -8.46,
      "pct_change": -2.12
    },
    {
      "symbol": "ORCL",
      "price": 183.36,
      "change": -3.36,
      "pct_change": -1.8
    }
  ]
}