{
  "items": [
    {
      "title": "Iran War Live Updates: Vance Issues Blunt Warning to Israel as He Defends Trump\u2019s Deal",
      "link": "https://www.nytimes.com/live/2026/06/18/world/iran-war-trump-us-deal",
      "source": "NYT",
      "published": "2026-06-18T19:06:19+00:00"
    },
    {
      "title": "Gunmen Attack a Major Airport in Niger",
      "link": "https://www.nytimes.com/2026/06/18/world/africa/niger-armed-attack-airport.html",
      "source": "NYT",
      "published": "2026-06-18T18:42:39+00:00"
    },
    {
      "title": "Man arrested on suspicion of attempted murder after boy injured in crocodile enclosure",
      "link": "https://www.bbc.com/news/articles/czx50n2vj74o?at_medium=RSS&at_campaign=rss",
      "source": "BBC",
      "published": "2026-06-18T18:27:37+00:00"
    },
    {
      "title": "Student loan borrowers will get an interest rate cut if they sign up for auto pay",
      "link": "https://www.npr.org/2026/06/18/nx-s1-5863085/student-loan-auto-pay-discount",
      "source": "NPR",
      "published": "2026-06-18T17:28:44+00:00"
    },
    {
      "title": "Read the full text of Trump's preliminary U.S.-Iran agreement to end the war",
      "link": "https://www.npr.org/2026/06/18/nx-s1-5863027/us-iran-trump-memorandum-of-understanding-full-text",
      "source": "NPR",
      "published": "2026-06-18T16:31:41+00:00"
    },
    {
      "title": "Ukraine hits a Moscow oil refinery and other sites in a large-scale drone attack",
      "link": "https://www.npr.org/2026/06/18/g-s1-128782/moscow-ukraine-drone-attack-russia-oil-refinery",
      "source": "NPR",
      "published": "2026-06-18T16:12:18+00:00"
    },
    {
      "title": "Ukraine Strikes Moscow Refinery in Large-Scale Drone Attack",
      "link": "https://www.nytimes.com/2026/06/18/world/europe/moscow-ukraine-drone-attack-fire.html",
      "source": "NYT",
      "published": "2026-06-18T16:11:41+00:00"
    },
    {
      "title": "Iran and the U.S. Have an Understanding. Will It Lead to a Deal?",
      "link": "https://www.nytimes.com/2026/06/18/world/europe/iran-united-states-deal-israel.html",
      "source": "NYT",
      "published": "2026-06-18T16:07:43+00:00"
    },
    {
      "title": "You're probably using too many skin care products. Here are the 3 essentials",
      "link": "https://www.npr.org/2026/06/18/nx-s1-5861903/essential-skin-care-products",
      "source": "NPR",
      "published": "2026-06-18T16:03:24+00:00"
    },
    {
      "title": "Bowen: US-Iran deal raises inescapable question of what the war was for",
      "link": "https://www.bbc.com/news/articles/clyegr2mp8jo?at_medium=RSS&at_campaign=rss",
      "source": "BBC",
      "published": "2026-06-18T15:53:55+00:00"
    }
  ]
}