{
  "items": [
    {
      "title": "At least 13 killed in 'most massive' Russian attack on Kyiv",
      "link": "https://www.bbc.co.uk/news/articles/c4gyv05gk4do?at_medium=RSS&at_campaign=rss",
      "source": "BBC",
      "published": "2026-07-02T09:15:16+00:00"
    },
    {
      "title": "Victims of forced adoption to get formal apology after years campaigning",
      "link": "https://www.bbc.co.uk/news/articles/c20yq332018o?at_medium=RSS&at_campaign=rss",
      "source": "BBC",
      "published": "2026-07-02T09:06:52+00:00"
    },
    {
      "title": "Federal civil rights data holds schools accountable. Under Trump, it's 6 months late",
      "link": "https://www.npr.org/2026/07/02/nx-s1-5859422/civil-rights-data-students-education",
      "source": "NPR",
      "published": "2026-07-02T09:00:00+00:00"
    },
    {
      "title": "Vatican declares Society of St. Pius X in schism, excommunicates bishops",
      "link": "https://www.npr.org/2026/07/02/nx-s1-5878916/vatican-society-of-st-pius-x-in-schism",
      "source": "NPR",
      "published": "2026-07-02T08:54:48+00:00"
    },
    {
      "title": "U.S. and Iran hold separate meetings in Qatar and agree to continue discussions",
      "link": "https://www.npr.org/2026/07/02/nx-s1-5878887/us-iran-meetings-qatar",
      "source": "NPR",
      "published": "2026-07-02T05:57:33+00:00"
    },
    {
      "title": "Russian missiles and drones kill 11 and cause damage across Ukraine capital",
      "link": "https://www.npr.org/2026/07/02/g-s1-131681/russian-attack-ukraine",
      "source": "NPR",
      "published": "2026-07-02T05:47:53+00:00"
    },
    {
      "title": "Watch: People smuggler tracked down and confronted by BBC",
      "link": "https://www.bbc.co.uk/news/videos/cnv9648nd5vo?at_medium=RSS&at_campaign=rss",
      "source": "BBC",
      "published": "2026-07-02T05:08:30+00:00"
    },
    {
      "title": "People smuggler convicted in France found by BBC living in UK and seeking asylum",
      "link": "https://www.bbc.co.uk/news/articles/clye9zn0y1ro?at_medium=RSS&at_campaign=rss",
      "source": "BBC",
      "published": "2026-07-02T05:00:03+00:00"
    },
    {
      "title": "Don't expect inbuilt trackers to save your stolen car, experts say",
      "link": "https://www.bbc.co.uk/news/articles/cp8r1798kp7o?at_medium=RSS&at_campaign=rss",
      "source": "BBC",
      "published": "2026-07-01T23:31:43+00:00"
    },
    {
      "title": "As Earthquake Death Toll Mounts, Venezuela Grapples With Recovering and Burying Bodies",
      "link": "https://www.nytimes.com/2026/07/01/world/americas/venezuela-earthquakes-bodies-morgues.html",
      "source": "NYT",
      "published": "2026-07-01T21:21:29+00:00"
    }
  ]
}