{
  "items": [
    {
      "title": "Who's in the cabinet?",
      "link": "https://www.bbc.co.uk/news/articles/ckg4we9g58do?at_medium=RSS&at_campaign=rss",
      "source": "BBC",
      "published": "2026-07-20T18:59:15+00:00"
    },
    {
      "title": "Israel\u2019s Ambassador to U.N. Lashes Out at Mamdani Over Netanyahu Arrest Threats",
      "link": "https://www.nytimes.com/2026/07/20/world/middleeast/israel-un-mamdani-netanyahu-arrest.html",
      "source": "NYT",
      "published": "2026-07-20T18:57:23+00:00"
    },
    {
      "title": "In Venezuela\u2019s Rubble, a Search for the Family Pets",
      "link": "https://www.nytimes.com/2026/07/20/world/americas/venezuela-earthquakes-volunteer-pets.html",
      "source": "NYT",
      "published": "2026-07-20T18:51:24+00:00"
    },
    {
      "title": "John Healey becomes chancellor weeks after shock resignation from defence job",
      "link": "https://www.bbc.co.uk/news/articles/ce85y9lm81no?at_medium=RSS&at_campaign=rss",
      "source": "BBC",
      "published": "2026-07-20T18:44:55+00:00"
    },
    {
      "title": "Key takeaways as Andy Burnham becomes PM",
      "link": "https://www.bbc.co.uk/news/articles/c80nln7zgp7o?at_medium=RSS&at_campaign=rss",
      "source": "BBC",
      "published": "2026-07-20T18:29:18+00:00"
    },
    {
      "title": "Burnham promises help with your money. How could it affect you?",
      "link": "https://www.bbc.co.uk/news/articles/cp9ezldrkkgo?at_medium=RSS&at_campaign=rss",
      "source": "BBC",
      "published": "2026-07-20T18:22:46+00:00"
    },
    {
      "title": "Faisal Islam: The new PM has big ideas - but what will they cost?",
      "link": "https://www.bbc.co.uk/news/articles/c9357rlk494o?at_medium=RSS&at_campaign=rss",
      "source": "BBC",
      "published": "2026-07-20T18:21:31+00:00"
    },
    {
      "title": "Inside the Deadly U.S. Airstrike on a Shadow Fleet Tanker",
      "link": "https://www.nytimes.com/2026/07/20/world/middleeast/inside-the-deadly-us-airstrike-on-a-shadow-fleet-tanker.html",
      "source": "NYT",
      "published": "2026-07-20T18:13:58+00:00"
    },
    {
      "title": "Court ruling freezes Paramount-Warner Bros. merger for now",
      "link": "https://www.npr.org/2026/07/20/nx-s1-5900888/paramount-wbd-tro-restraining-lawsuit",
      "source": "NPR",
      "published": "2026-07-20T17:55:31+00:00"
    },
    {
      "title": "Outcry in Italy After Man Dies While Being Restrained by Police",
      "link": "https://www.nytimes.com/2026/07/20/world/europe/moroccan-italy-police-death-george-floyd.html",
      "source": "NYT",
      "published": "2026-07-20T17:40:40+00:00"
    }
  ]
}