{
  "leaderboard": {
    "tournament": "Genesis Scottish Open",
    "status": "In Progress",
    "players": [
      {
        "position": "1",
        "name": "Johnny Keefer",
        "total": "-10",
        "round_score": "-",
        "thru": "0"
      },
      {
        "position": "T-2",
        "name": "Marcus Armitage",
        "total": "-9",
        "round_score": "-",
        "thru": "0"
      },
      {
        "position": "T-2",
        "name": "Kevin Roy",
        "total": "-9",
        "round_score": "-",
        "thru": "0"
      },
      {
        "position": "T-2",
        "name": "Wyndham Clark",
        "total": "-9",
        "round_score": "-",
        "thru": "0"
      },
      {
        "position": "T-2",
        "name": "Jordan Smith",
        "total": "-9",
        "round_score": "-",
        "thru": "0"
      },
      {
        "position": "T-2",
        "name": "Rory McIlroy",
        "total": "-9",
        "round_score": "-",
        "thru": "0"
      },
      {
        "position": "T-2",
        "name": "Tom Kim",
        "total": "-9",
        "round_score": "-",
        "thru": "0"
      },
      {
        "position": "T-8",
        "name": "Mac Meissner",
        "total": "-8",
        "round_score": "-",
        "thru": "0"
      },
      {
        "position": "T-8",
        "name": "Rasmus Neergaard-Petersen",
        "total": "-8",
        "round_score": "-",
        "thru": "0"
      },
      {
        "position": "T-8",
        "name": "Michael Thorbjornsen",
        "total": "-8",
        "round_score": "-",
        "thru": "0"
      }
    ]
  }
}