{
  "leaderboard": {
    "tournament": "Travelers Championship",
    "status": "In Progress",
    "players": [
      {
        "position": "T-1",
        "name": "Tom Hoge",
        "total": "-3",
        "round_score": "-",
        "thru": "0"
      },
      {
        "position": "T-1",
        "name": "Eric Cole",
        "total": "-3",
        "round_score": "-",
        "thru": "0"
      },
      {
        "position": "T-1",
        "name": "Ben James",
        "total": "-3",
        "round_score": "-",
        "thru": "0"
      },
      {
        "position": "T-4",
        "name": "Robert MacIntyre",
        "total": "-2",
        "round_score": "-",
        "thru": "0"
      },
      {
        "position": "T-4",
        "name": "Harry Hall",
        "total": "-2",
        "round_score": "-",
        "thru": "0"
      },
      {
        "position": "T-4",
        "name": "Ben Griffin",
        "total": "-2",
        "round_score": "-",
        "thru": "0"
      },
      {
        "position": "T-4",
        "name": "Nick Taylor",
        "total": "-2",
        "round_score": "-",
        "thru": "0"
      },
      {
        "position": "T-4",
        "name": "Matt Fitzpatrick",
        "total": "-2",
        "round_score": "-",
        "thru": "0"
      },
      {
        "position": "T-9",
        "name": "Matt McCarty",
        "total": "-1",
        "round_score": "-",
        "thru": "0"
      },
      {
        "position": "T-9",
        "name": "Jackson Suber",
        "total": "-1",
        "round_score": "-",
        "thru": "0"
      }
    ]
  }
}