{
  "leaderboard": {
    "tournament": "Travelers Championship",
    "status": "In Progress",
    "players": [
      {
        "position": "T-1",
        "name": "Viktor Hovland",
        "total": "-16",
        "round_score": "-",
        "thru": "0"
      },
      {
        "position": "T-1",
        "name": "Akshay Bhatia",
        "total": "-16",
        "round_score": "-",
        "thru": "0"
      },
      {
        "position": "T-1",
        "name": "Scottie Scheffler",
        "total": "-16",
        "round_score": "-",
        "thru": "0"
      },
      {
        "position": "4",
        "name": "Patrick Cantlay",
        "total": "-14",
        "round_score": "-",
        "thru": "0"
      },
      {
        "position": "T-5",
        "name": "Shane Lowry",
        "total": "-13",
        "round_score": "-",
        "thru": "0"
      },
      {
        "position": "T-5",
        "name": "Wyndham Clark",
        "total": "-13",
        "round_score": "-",
        "thru": "0"
      },
      {
        "position": "T-7",
        "name": "Keith Mitchell",
        "total": "-12",
        "round_score": "-",
        "thru": "0"
      },
      {
        "position": "T-7",
        "name": "Si Woo Kim",
        "total": "-12",
        "round_score": "-",
        "thru": "0"
      },
      {
        "position": "T-7",
        "name": "Maverick McNealy",
        "total": "-12",
        "round_score": "-",
        "thru": "0"
      },
      {
        "position": "T-7",
        "name": "Justin Rose",
        "total": "-12",
        "round_score": "-",
        "thru": "0"
      }
    ]
  }
}