{
  "leaderboard": {
    "tournament": "RBC Canadian Open",
    "status": "Final",
    "players": [
      {
        "position": "1",
        "name": "Bud Cauley",
        "total": "-17",
        "round_score": "-5",
        "thru": "F"
      },
      {
        "position": "2",
        "name": "Matt Fitzpatrick",
        "total": "-15",
        "round_score": "-6",
        "thru": "F"
      },
      {
        "position": "3",
        "name": "Viktor Hovland",
        "total": "-14",
        "round_score": "-5",
        "thru": "F"
      },
      {
        "position": "T-4",
        "name": "Jimmy Stanger",
        "total": "-13",
        "round_score": "-3",
        "thru": "F"
      },
      {
        "position": "T-4",
        "name": "Brice Garnett",
        "total": "-13",
        "round_score": "-2",
        "thru": "F"
      },
      {
        "position": "T-4",
        "name": "Jesper Svensson",
        "total": "-13",
        "round_score": "-2",
        "thru": "F"
      },
      {
        "position": "T-4",
        "name": "Jackson Suber",
        "total": "-13",
        "round_score": "E",
        "thru": "F"
      },
      {
        "position": "T-8",
        "name": "Aldrich Potgieter",
        "total": "-12",
        "round_score": "-5",
        "thru": "F"
      },
      {
        "position": "T-8",
        "name": "Sudarshan Yellamaraju",
        "total": "-12",
        "round_score": "-2",
        "thru": "F"
      },
      {
        "position": "T-8",
        "name": "Ryan Fox",
        "total": "-12",
        "round_score": "-2",
        "thru": "F"
      }
    ]
  }
}