{
  "leaderboard": {
    "tournament": "the Memorial Tournament pres. by Workday",
    "status": "Final",
    "players": [
      {
        "position": "T-1",
        "name": "J.T. Poston",
        "total": "-12",
        "round_score": "-",
        "thru": "0"
      },
      {
        "position": "T-1",
        "name": "Ryan Gerard",
        "total": "-12",
        "round_score": "-",
        "thru": "0"
      },
      {
        "position": "3",
        "name": "Wyndham Clark",
        "total": "-11",
        "round_score": "-5",
        "thru": "F"
      },
      {
        "position": "T-4",
        "name": "Tommy Fleetwood",
        "total": "-10",
        "round_score": "-4",
        "thru": "F"
      },
      {
        "position": "T-4",
        "name": "Sam Burns",
        "total": "-10",
        "round_score": "-3",
        "thru": "F"
      },
      {
        "position": "T-6",
        "name": "Kristoffer Reitan",
        "total": "-8",
        "round_score": "-7",
        "thru": "F"
      },
      {
        "position": "T-6",
        "name": "Alex Fitzpatrick",
        "total": "-8",
        "round_score": "-7",
        "thru": "F"
      },
      {
        "position": "8",
        "name": "Eric Cole",
        "total": "-7",
        "round_score": "-2",
        "thru": "F"
      },
      {
        "position": "9",
        "name": "Alex Noren",
        "total": "-6",
        "round_score": "-2",
        "thru": "F"
      },
      {
        "position": "T-10",
        "name": "Si Woo Kim",
        "total": "-5",
        "round_score": "-6",
        "thru": "F"
      }
    ]
  }
}